[

    {
        "nome": "Ana",
        "sobrenome": "Lucia",
        "empresa": "Ebac",
        "endereco": "Av. Paulista",
        "numero": "2000",
        "pais": "Brasil",
        "cidade": "São Paulo",
        "estado": "São Paulo",
        "cep": "01001000",
        "telefone": "11999999",
        "email": "teste@teste.com"

    },

    {
        "nome": "João",
        "sobrenome": "Lucio",
        "empresa": "Google",
        "endereco": "Av. Paulista",
        "numero": "2000",
        "pais": "Brasil",
        "cidade": "São Paulo",
        "estado": "São Paulo",
        "cep": "01001000",
        "telefone": "11999999",
        "email": "teste@teste.com"

    },

    {
        "nome": "Astolfo",
        "sobrenome": "Adolfo",
        "empresa": "Meta",
        "endereco": "Av. Chavinho",
        "numero": "71",
        "pais": "Holanda",
        "cidade": "São Paulo",
        "estado": "São Paulo",
        "cep": "01001000",
        "telefone": "11999999",
        "email": "teste@teste.com"

    }


]